pytest_dockerc/__init__.py
pytest_dockerc/fixtures.py
pytest_dockerc/plugin.py
pytest_dockerc-1.0.8.dist-info/AUTHORS
pytest_dockerc-1.0.8.dist-info/LICENSE
pytest_dockerc-1.0.8.dist-info/METADATA
pytest_dockerc-1.0.8.dist-info/WHEEL
pytest_dockerc-1.0.8.dist-info/entry_points.txt
pytest_dockerc-1.0.8.dist-info/top_level.txt
pytest_dockerc-1.0.8.dist-info/RECORD
