Metadata-Version: 2.1
Name: pytest-dockerc
Version: 1.0.8
Summary: Run, manage and stop Docker Compose project from Docker API
Home-page: https://gitlab.com/nicofonk/pytest-dockerc
Author: Nicolas Gelot
Author-email: nicolas.gelot@vadesecure.com
License: MIT
Keywords: py.test pytest docker docker-compose container
Platform: UNKNOWN
Classifier: Development Status :: 5 - Production/Stable
Classifier: Framework :: Pytest
Classifier: Intended Audience :: Developers
Classifier: Operating System :: POSIX
Classifier: Operating System :: Microsoft :: Windows
Classifier: Operating System :: MacOS :: MacOS X
Classifier: Topic :: Software Development :: Quality Assurance
Classifier: Topic :: Software Development :: Testing
Classifier: Topic :: Utilities
Classifier: Programming Language :: Python
Classifier: Programming Language :: Python :: 2.7
Classifier: Programming Language :: Python :: 3.6
Classifier: Programming Language :: Python :: 3.7
Requires-Dist: pytest (>=3.0)
Requires-Dist: docker-compose (>=1.17.1)
Provides-Extra: tests
Requires-Dist: requests ; extra == 'tests'
